pat_cli/__init__.py
pat_cli/args.py
pat_cli/main.py
pat_cli/tokenization.py
pat_cli/vectorization.py
pat_cli-0.2.1.dist-info/LICENSE
pat_cli-0.2.1.dist-info/METADATA
pat_cli-0.2.1.dist-info/WHEEL
pat_cli-0.2.1.dist-info/entry_points.txt
pat_cli-0.2.1.dist-info/RECORD
