Metadata-Version: 2.1
Name: pat-cli
Version: 0.2.1
Summary: 
Author: Rafid Al-Humaimidi
Author-email: rafidka@gmail.com
Requires-Python: >=3.12,<4.0
Classifier: Programming Language :: Python :: 3
Classifier: Programming Language :: Python :: 3.12
Classifier: Programming Language :: Python :: 3.13
Requires-Dist: fasttext (>=0.9.3,<0.10.0)
Requires-Dist: nltk (>=3.9.1,<4.0.0)
Requires-Dist: numpy (>=2.1.3,<3.0.0)
Requires-Dist: pandas (>=2.2.3,<3.0.0)
Requires-Dist: scikit-learn (>=1.5.2,<2.0.0)
Requires-Dist: termcolor (>=2.5.0,<3.0.0)
